asynchelpers/__init__.py
asynchelpers/_config.py
asynchelpers/core.py
asynchelpers/utils.py
asynchelpers-1.2.0.dist-info/METADATA
asynchelpers-1.2.0.dist-info/WHEEL
asynchelpers-1.2.0.dist-info/top_level.txt
asynchelpers-1.2.0.dist-info/RECORD
