Metadata-Version: 2.2
Name: asynchelpers
Version: 1.2.0
Summary: Asynchronous utilities with runtime optimizations
Author: Async Tools Ltd
Author-email: support@async-tools.com
Classifier: Programming Language :: Python :: 3
Classifier: License :: OSI Approved :: Apache Software License
Requires-Python: >=3.8
Requires-Dist: aiohttp>=3.9.0
Dynamic: author
Dynamic: author-email
Dynamic: classifier
Dynamic: description
Dynamic: description-content-type
Dynamic: requires-dist
Dynamic: requires-python
Dynamic: summary
